mkvtomp4-2.0.data/data/share/doc/mkvtomp4/LICENSE
mkvtomp4-2.0.data/data/share/doc/mkvtomp4/README.mkd
mkvtomp4-2.0.data/data/share/doc/mkvtomp4/mkvtomp4.txt
mkvtomp4-2.0.data/data/share/man/man1/mkvtomp4.1
mkvtomp4-2.0.data/data/share/man/man1/mkvtomp4.1.html
mkvtomp4-2.0.data/scripts/mkvtomp4.py
mkvtomp4-2.0.dist-info/DESCRIPTION.rst
mkvtomp4-2.0.dist-info/METADATA
mkvtomp4-2.0.dist-info/RECORD
mkvtomp4-2.0.dist-info/WHEEL
mkvtomp4-2.0.dist-info/metadata.json
mkvtomp4-2.0.dist-info/top_level.txt
simplemkv/__init__.py
simplemkv/info.py
simplemkv/tomp4.py
simplemkv/version.py
